groundingdino/__init__.py
groundingdino/version.py
groundingdino/config/GroundingDINO_SwinB_cfg.py
groundingdino/config/GroundingDINO_SwinT_OGC.py
groundingdino/config/__init__.py
groundingdino/datasets/__init__.py
groundingdino/datasets/cocogrounding_eval.py
groundingdino/datasets/transforms.py
groundingdino/models/__init__.py
groundingdino/models/registry.py
groundingdino/models/GroundingDINO/__init__.py
groundingdino/models/GroundingDINO/bertwarper.py
groundingdino/models/GroundingDINO/fuse_modules.py
groundingdino/models/GroundingDINO/groundingdino.py
groundingdino/models/GroundingDINO/ms_deform_attn.py
groundingdino/models/GroundingDINO/transformer.py
groundingdino/models/GroundingDINO/transformer_vanilla.py
groundingdino/models/GroundingDINO/utils.py
groundingdino/models/GroundingDINO/backbone/__init__.py
groundingdino/models/GroundingDINO/backbone/backbone.py
groundingdino/models/GroundingDINO/backbone/position_encoding.py
groundingdino/models/GroundingDINO/backbone/swin_transformer.py
groundingdino/util/__init__.py
groundingdino/util/box_ops.py
groundingdino/util/get_tokenlizer.py
groundingdino/util/inference.py
groundingdino/util/logger.py
groundingdino/util/misc.py
groundingdino/util/slconfig.py
groundingdino/util/slio.py
groundingdino/util/time_counter.py
groundingdino/util/utils.py
groundingdino/util/visualizer.py
groundingdino/util/vl_utils.py
gdinopy-1.1.0.dist-info/LICENSE
gdinopy-1.1.0.dist-info/METADATA
gdinopy-1.1.0.dist-info/WHEEL
gdinopy-1.1.0.dist-info/top_level.txt
gdinopy-1.1.0.dist-info/RECORD
