Metadata-Version: 2.1
Name: gdinopy
Version: 1.1.0
Summary: open-set object detector
Home-page: https://github.com/IDEA-Research/GroundingDINO
Author: International Digital Economy Academy, Shilong Liu
License: Apache License
License-File: LICENSE
Requires-Dist: numpy >=1.23.5
Requires-Dist: torch >=2.0.0
Requires-Dist: torchvision >=0.15.1
Requires-Dist: timm >=0.9.16
Requires-Dist: opencv-python >=4.9.0.80
Requires-Dist: supervision >=0.19.0
Requires-Dist: pycocotools >=2.0.7
Requires-Dist: transformers >=4.39.2
Requires-Dist: addict >=2.4.0
Requires-Dist: yapf >=0.40.2
